{
    "type": "sewingkit:sewing",
    "materials": [
      {
        "ingredient": {
          "item": "iceandfire:sea_serpent_scales_bronze"
        },
        "count": 4
      },
      {
        "ingredient": {
          "item": "iceandfire:shiny_scales"
        },
        "count": 2
      },
      {
        "ingredient": {
          "tag": "forge:string"
        },
        "count": 2
      }
    ],
    "result": {
      "item": "iceandfire:tide_bronze_leggings"
    },
    "tool": {
      "type": "sewingkit:tool_ingredient",
      "tool_type": "sewing_needle",
      "tool_level": 2
    }
}